fmtspec/__init__.py
fmtspec/py.typed
fmtspec-0.1.0.dist-info/WHEEL
fmtspec-0.1.0.dist-info/METADATA
fmtspec-0.1.0.dist-info/RECORD
