Metadata-Version: 2.3
Name: fmtspec
Version: 0.1.0
Summary: A flexible binary format serialization library for Python
Author: Peter Gessler
Author-email: Peter Gessler <gesslerpd@users.noreply.github.com>
Requires-Dist: msgspec>=0.20.0
Requires-Python: >=3.12
